mm_rpa_utils/__init__.py
mm_rpa_utils/funciones.py
mm_rpa_utils-0.1.0.dist-info/METADATA
mm_rpa_utils-0.1.0.dist-info/WHEEL
mm_rpa_utils-0.1.0.dist-info/top_level.txt
mm_rpa_utils-0.1.0.dist-info/RECORD
